app/__init__.py
app/main.py
flasker_project-0.0.1.dist-info/LICENSE
flasker_project-0.0.1.dist-info/METADATA
flasker_project-0.0.1.dist-info/WHEEL
flasker_project-0.0.1.dist-info/top_level.txt
flasker_project-0.0.1.dist-info/RECORD
