Metadata-Version: 2.1
Name: flasker-project
Version: 0.0.1
Summary: A small package to quickly create a very simple flask project
Home-page: https://github.com/kangah-codes/flasker
Author: Joshua Akangah
Author-email: joshua@thecodekangaroo.com
License: UNKNOWN
Platform: UNKNOWN
Classifier: Programming Language :: Python :: 3
Classifier: License :: OSI Approved :: MIT License
Classifier: Operating System :: OS Independent
Requires-Python: >=3.6
